mkdocs_to_kirby/__init__.py
mkdocs_to_kirby/config.py
mkdocs_to_kirby/kirby.py
mkdocs_to_kirby/plugin.py
mkdocs_to_kirby-0.11.2.dist-info/METADATA
mkdocs_to_kirby-0.11.2.dist-info/WHEEL
mkdocs_to_kirby-0.11.2.dist-info/entry_points.txt
mkdocs_to_kirby-0.11.2.dist-info/top_level.txt
mkdocs_to_kirby-0.11.2.dist-info/RECORD
