Metadata-Version: 2.4
Name: mkdocs-to-kirby
Version: 0.11.2
Summary: Mkdocs plugin to kirby content structure
License: MIT
Project-URL: Homepage, https://github.com/kreemer/mkdocs-to-kirby
Keywords: mkdocs,kirby,plugin
Classifier: Operating System :: OS Independent
Classifier: Programming Language :: Python
Classifier: Programming Language :: Python :: 3
Classifier: Programming Language :: Python :: 3.11
Classifier: Programming Language :: Python :: 3.12
Classifier: Programming Language :: Python :: 3.13
Classifier: Programming Language :: Python :: 3 :: Only
Classifier: License :: OSI Approved :: MIT License
Classifier: Topic :: Documentation
Classifier: Topic :: Text Processing
Requires-Python: >=3.11
Requires-Dist: mkdocs>=1.0
